{
    "id": "micro-ch1-intro",
    "course": "microeconomics",
    "chapterNumber": 1,
    "totalChapters": 12,
    "title": "מהו מדע הכלכלה?",
    "navigation": {
        "previous": null,
        "next": {
            "id": "chapter-2",
            "title": "עלות אלטרנטיבית"
        }
    },
    "pageMap": {
        "learningObjectives": [
            "להבין מהו מדע הכלכלה ולמה הוא שייך למדעי החברה",
            "להגדיר את תופעת המחסור כבסיס לכל החלטה כלכלית",
            "להבחין בין מוצר כלכלי למוצר חופשי",
            "להכיר את שלושת גורמי היצור: טבע, עבודה והון"
        ],
        "prerequisites": [],
        "estimatedTime": "30 דקות"
    },
    "introduction": {
        "content": "למה אנחנו לומדים כלכלה? לא בגלל כסף, אלא בגלל בחירות. העולם שלנו מתנהל תחת תנאי אחד קשוח: יש לנו רצונות אינסופיים, אבל משאבים מוגבלים. בפרק הזה נבין איך הקונפליקט הזה מייצר את המדע שנקרא כלכלה, ונלמד להבחין בין סוגי המוצרים השונים וגורמי היצור שמרכיבים את העולם שלנו.",
        "whyItMatters": "בלי להבין מחסור, אי אפשר להבין מחירים, תמריצים או התנהגות אנושית."
    },
    "teaserAnalogy": {
        "content": "דמיין שאתה יושב מול נטפליקס ביום חמישי בערב. יש לך בדיוק שעתיים לפני שאתה חייב לישון (משאב מוגבל), אבל יש לך 50 סדרות שאתה חייב לראות (רצונות אינסופיים). ברגע שבחרת סדרה אחת — ויתרת על אחרות. ברכותיי, אתה מנהל מיקרו-כלכלה פרטית."
    },
    "formalDefinitions": {
        "concepts": [
            {
                "title": "מחסור (Scarcity)",
                "content": "תופעה שבה כמות המשאבים בעולם מוגבלת, בעוד הצרכים והרצונות של בני האדם הם בלתי מוגבלים. זהו הבסיס לכל הכלכלה.",
                "tooltips": {
                    "מחסור": "הפער התמידי בין רצוי למצוי"
                }
            },
            {
                "title": "יעילות ביצור (Production Efficiency)",
                "content": "מצב שבו לא ניתן לייצר עוד יחידה ממוצר אחד מבלי לוותר על ייצור של מוצר אחר. זהו המבחן האולטימטיבי לניצול נכון של משאבים.",
                "tooltips": {
                    "יעילות": "המקסימום האפשרי מהמשאבים הנתונים"
                }
            },
            {
                "title": "עקומת התמורה (PPC)",
                "content": "הגבול הגיאומטרי של אפשרויות היצור במשק. כל נקודה על העקומה מייצגת הקצאה יעילה (תעסוקה מלאה ויעילות ביצור).",
                "tooltips": {
                    "עקומה": "אוסף כל ההקצאות היעילות במשק"
                }
            },
            {
                "title": "גורמי יצור (Factors of Production)",
                "content": "המשאבים הדרושים ליצור: 1. טבע (קרקע, מחצבים). 2. עבודה (הון אנושי, זמן). 3. הון פיזי (מכונות, מבנים, ציוד).",
                "tooltips": {
                    "הון פיזי": "משאבים שיוצרו בעבר כדי לייצר בעתיד (לא כסף!)"
                }
            }
        ],
        "formulas": []
    },
    "toneBreak": {
        "opener": "אז מה זה אומר, תכל'ס?",
        "content": "אוקיי, בוא נוריד את זה לקרקע. 📉\\n\\nמחסור = אין מספיק לכולם. זה לא אומר שחסר 'כסף', זה אומר שגם אם היה לך את כל הכסף בעולם, הזמן שלך עדיין מוגבל. \\n\\nגורמי יצור = המצרכים לעוגה שנקראת 'מוצר'. אתה צריך אדמה (טבע), מישהו שיכין (עבודה) ותנור (הון פיזי).\\n\\nבקיצור: כלכלה זה המדע של הבאסה מזה שאי אפשר לקבל הכל יחד. 😎",
        "academicTitle": "סקירה תיאורטית: בעיית המחסור",
        "academicContent": "מדע הכלכלה עוסק בחקר הקצאת מקורות (Means) המצויים בצמצום (Scarcity) אל מול ריבוי צרכים (Ends). הנחת היסוד היא שמשאבי הייצור - קרקע, עבודה והון - הם סופיים בכל נקודת זמן נתונה, בעוד שרצונות הפרטים הם אינסופיים. המתח המבני הזה מחייב קבלת החלטות ווויתור על אלטרנטיבות (Trade-offs), והוא המנוע של הפעילות הכלכלית כולה."
    },
    "deepDive": {
        "determinants": [
            {
                "title": "הפרדוקס של יעילות (Pareto)",
                "content": "איך יודעים אם אנחנו יעילים? המבחן הוא פשוט אך אכזרי: אם אפשר לייצר עוד ממוצר X **מבלי** לפגוע בייצור של Y, סימן שהיינו **בזבזנים** קודם לכן (נקודה בתוך העקומה). יעילות מושגת רק כשכל שיפור דורש הקרבה.",
                "subItems": [
                    {
                        "label": "מבחן השלילה",
                        "value": "אם ניתן לתת למישהו 'חינם' (בלי לקחת מאחר) - המצב לא יעיל."
                    },
                    {
                        "label": "אבטלה מבנית",
                        "value": "קיום מכונות ללא עובדים מיומנים יוצר חוסר יעילות, גם אם יש 'רצון' לייצר."
                    }
                ]
            }
        ],
        "examAppearance": {
            "commonFormats": [
                "מיון מוצרים לחופשיים מול כלכליים בסיטואציות שונות",
                "זיהוי גורמי יצור בתיאור של פירמה",
                "שאלות תיאורטיות על הגדרת המחסור"
            ],
            "tips": [
                "שימו לב: 'זמן' הוא המשאב הכי בסיסי במחסור, גם אם לא מוזכר מפורשות.",
                "אל תתבלבלו בין הון פיזי (מכונה) להון כספי (כסף בבנק)."
            ],
            "keyPhrases": [
                "תופעת המחסור",
                "עלות אלטרנטיבית",
                "ויתור ריאלי",
                "משאבים מוגבלים",
                "רצונות אינסופיים"
            ]
        }
    },
    "commonMistakes": [
        {
            "mistake": "לחשוב שמחסור (Scarcity) זה אותו דבר כמו גירעון (Shortage)",
            "correct": "מחסור הוא מצב קבוע. גירעון הוא מצב זמני שבו במחיר מסוים הביקוש גבוה מההיצע.",
            "why": "מחסור תמיד קיים, גם כשהמדפים בסופר מלאים."
        }
    ],
    "interactiveElement": {
        "type": "classification-game",
        "title": "סווג את המוצר!",
        "instructions": "גרור כל פריט לקטגוריה הנכונה: מוצר כלכלי או מוצר חופשי",
        "items": [
            {
                "label": "אוויר בטיילת",
                "correctCategory": "מוצר חופשי"
            },
            {
                "label": "אוויר בצוללת",
                "correctCategory": "מוצר כלכלי"
            },
            {
                "label": "מי ברזה",
                "correctCategory": "מוצר כלכלי"
            },
            {
                "label": "קרני שמש בחוף",
                "correctCategory": "מוצר חופשי"
            }
        ]
    },
    "checkpoint": [
        {
            "id": "q1",
            "type": "multipleChoice",
            "text": "האם מיליארדר שחי באי בודד עם כל המותרות שניתן לקנות, עדיין מתמודד עם תופעת המחסור?",
            "options": [
                "לא, יש לו את כל המשאבים שהוא צריך",
                "כן, כי זמנו עדיין מוגבל",
                "לא, כי הוא לא צריך לסחור עם אחרים",
                "רק אם הוא רוצה לקנות משהו שאין באי"
            ],
            "correctIndex": 1,
            "explanation": "מחסור הוא תופעה יסודית שנובעת מכך שהזמן והגוף שלנו סופיים, ללא קשר לעושר."
        }
    ],
    "streetSummary": {
        "content": "בוא נסגור פינה: מדע הכלכלה זה לא רק 'בורסה' ו'נתוני מאקרו'. זה הסיפור של איך אנחנו מחליטים מה לעשות בבוקר עם המשאבים המאוד מצומצמים שלנו (בעיקר זמן ואנרגיה). אם הכל היה חופשי ובשפע, הכלכלנים היו הולכים לים. אבל בגלל שהכל עולה בוויתור — אנחנו כאן."
    },
    "guidedExercises": [
        {
            "difficulty": 2,
            "question": "במשק יש 100 עובדים. כל עובד יכול לייצר ביום מנת פלאפל אחת (X) או 2 מנות חומוס (Y). המשק מייצר כרגע 50 פלאפל ו-100 חומוס. האם ההקצאה יעילה?",
            "thinkingDirection": "בדוק שני דברים: 1. האם כולם עובדים? (אבטלה) 2. האם ניתן לייצר יותר מאחד בלי לוותר על השני?",
            "steps": [
                {
                    "title": "חישוב תעסוקה נדרשת",
                    "calculation": "50X + 100Y",
                    "reasoning": "לייצור 50 פלאפל צריך 50 עובדים (1:1). לייצור 100 חומוס צריך 50 עובדים (כל אחד מייצר 2)."
                },
                {
                    "title": "בדיקת סך המועסקים",
                    "calculation": "50 + 50 = 100",
                    "reasoning": "כל 100 העובדים מועסקים. כולם עובדים."
                },
                {
                    "title": "מבחן היעילות",
                    "calculation": "האם ניתן לייצר יותר?",
                    "reasoning": "לא ניתן לייצר עוד פלאפל מבלי לקחת עובד מייצור החומוס (ולכן להקטין את החומוס). לכן - ההקצאה יעילה."
                }
            ],
            "finalAnswer": "כן, ההקצאה יעילה (נמצאת על עקומת התמורה: X+0.5Y=100)."
        }
    ],
    "independentExercises": [
        {
            "difficulty": 2,
            "question": "אם אדם זוכה בלוטו, האם תופעת המחסור נעלמת עבורו?",
            "steps": [],
            "finalAnswer": "לא, כי הזמן שלו עדיין מוגבל והוא יצטרך לבחור איך לנצל אותו."
        }
    ],
    "quickReference": {
        "formulas": [],
        "definitions": [
            {
                "term": "מחסור",
                "definition": "פער בין רצונות למשאבים"
            },
            {
                "term": "הון פיזי",
                "definition": "מכונות ומבנים לייצור"
            }
        ]
    },
    "trivia": [
        {
            "fact": "השימוש הראשון במילה 'כלכלן' מיוחס ליוונים העתיקים, והוא תיאר את האדם שיודע לנהל את משק הבית בצורה חסכונית.",
            "type": "history"
        }
    ],
    "bridge": {
        "nextChapter": "chapter-2",
        "nextChapterTitle": "עלות אלטרנטיבית",
        "content": "עכשיו כשהבנו שיש מחסור וצריך לבחור, השאלה הבאה היא: כמה הבחירה הזו באמת עולה לנו?"
    }
}